[
{"link": "https://twitter.com/axmukher"},
{"link": "https://twitter.com/debdudeck"},
{"link": "https://twitter.com/jdm80email"},
{"link": "https://twitter.com/attitudeforty5"},
{"link": "https://twitter.com/stuyvesant19"},
{"link": "https://twitter.com/chrgdup1973"},
{"link": "https://twitter.com/Zayedfamily1"},
{"link": "https://twitter.com/joshuamead6982"},
{"link": "https://twitter.com/joseph_kandrot"},
{"link": "https://twitter.com/maker35"},
{"link": "https://twitter.com/PearsonSpr1nger"},
{"link": "https://twitter.com/tweetsaremythig"},
{"link": "https://twitter.com/dasef4real19"},
{"link": "https://twitter.com/Rightingtheship"},
{"link": "https://twitter.com/kltyler1957"},
{"link": "https://twitter.com/YassinFawaz"},
{"link": "https://twitter.com/DunceBiden"},
{"link": "https://twitter.com/Queendode"},
{"link": "https://twitter.com/nightwalker1889"},
{"link": "https://twitter.com/debperfetti"},
{"link": "https://twitter.com/Lbirdsville"},
{"link": "https://twitter.com/lusciouslindaw"},
{"link": "https://twitter.com/jmerrick82yaho1"},
{"link": "https://twitter.com/tedertuata1970"},
{"link": "https://twitter.com/TrumpsSquirrel"}
]